targon/__init__.py
targon/cache.py
targon/loggers.py
targon/queues.py
targon/savers.py
targon/targon.py
targon/addons/__init__.py
targon/addons/leona.py
targon/bootstrap/__init__.py
targon/bootstrap/accountId.py
targon/bootstrap/bootstrap.py
targon/bootstrap/leagueId.py
targon/bootstrap/matchId.py
targon/bootstrap/summonerId.py
targon/callers/__init__.py
targon/callers/base_caller.py
targon/callers/callers.py
targon/parsers/__init__.py
targon/parsers/parsers.py
targon/templates/__init__.py
targon/templates/match_template.py
targon-0.0.1a2.dist-info/METADATA
targon-0.0.1a2.dist-info/WHEEL
targon-0.0.1a2.dist-info/top_level.txt
targon-0.0.1a2.dist-info/RECORD
