Metadata-Version: 2.1
Name: targon
Version: 0.0.1a2
Summary: Library for Riot API crawlers
Home-page: https://github.com/Canisback/targon
Author: Canisback
Author-email: canisback@gmail.com
License: UNKNOWN
Keywords: Riot API,python,League of Legends
Platform: UNKNOWN
Requires-Dist: pantheon
Requires-Dist: sortedcontainers
